{
    "servers": [
        {
            "admin_pass": "xJXQhW7CwRHG",
            "id": "608fc6ec-4ef1-466b-82f2-84d4c4f79530",
            "links": [
                {
                    "href": "http://openstack.example.com/v3/servers/608fc6ec-4ef1-466b-82f2-84d4c4f79530",
                    "rel": "self"
                },
                {
                    "href": "http://openstack.example.com/servers/608fc6ec-4ef1-466b-82f2-84d4c4f79530",
                    "rel": "bookmark"
                }
            ]
        }
    ]
}